{"SANTAFE DE BOGOTA D.C": [{"city": "BOGOTA", "long": -74.0722, "lat": 4.7111, "cases": 27302}], "CAUCA": [{"city": "TIMBIO", "long": -76.6839, "lat": 2.3445, "cases": 267}, {"city": "POPAYAN", "long": -76.6092, "lat": 2.4542, "cases": 6426}, {"city": "SANTANDER DE QUILICHAO", "long": -76.4833, "lat": 3.0167, "cases": 1445}, {"city": "PUERTO TEJADA", "long": -76.4167, "lat": 3.25, "cases": 452}, {"city": "PIENDAMO", "long": -76.5284, "lat": 2.6408, "cases": 386}, {"city": "MIRANDA", "long": -76.25, "lat": 3.25, "cases": 168}, {"city": "CAJIBIO", "long": -76.6333, "lat": 2.6333, "cases": 210}, {"city": "PATIA", "long": -77.0833, "lat": 2.1667, "cases": 142}, {"city": "BUENOS AIRES", "long": -76.6667, "lat": 2.9167, "cases": 98}, {"city": "CALDONO", "long": -76.5333, "lat": 2.8, "cases": 97}, {"city": "CORINTO", "long": -76.2594, "lat": 3.1739, "cases": 170}, {"city": "SILVIA", "long": -76.3833, "lat": 2.6167, "cases": 136}, {"city": "INZA", "long": -76.0667, "lat": 2.55, "cases": 132}, {"city": "TORIBIO", "long": -76.2714, "lat": 2.9581, "cases": 111}, {"city": "BALBOA", "long": -77.2197, "lat": 2.0436, "cases": 125}, {"city": "CALOTO", "long": -76.4167, "lat": 3.0333, "cases": 538}, {"city": "GUAPI", "long": -77.8856, "lat": 2.5703, "cases": 150}, {"city": "TIMBIQUI", "long": -77.6333, "lat": 2.7667, "cases": 57}, {"city": "ALMAGUER", "long": -76.8667, "lat": 1.9167, "cases": 55}, {"city": "SUAREZ", "long": -76.6953, "lat": 2.9589, "cases": 92}, {"city": "VILLA RICA", "long": -76.85, "lat": 2.5167, "cases": 248}, {"city": "TOTORO", "long": -76.4003, "lat": 2.5117, "cases": 97}, {"city": "JAMBALO", "long": -76.3167, "lat": 2.85, "cases": 19}, {"city": "MERCADERES", "long": -77.1667, "lat": 1.8, "cases": 87}, {"city": "ROSAS", "long": -76.75, "lat": 2.2667, "cases": 47}, {"city": "LA SIERRA", "long": -76.8333, "lat": 2.25, "cases": 52}, {"city": "SAN SEBASTIAN", "long": -76.7717, "lat": 1.8439, "cases": 17}], "ANTIOQUIA": [{"city": "MEDELLIN", "long": -75.5906, "lat": 6.2308, "cases": 20638}, {"city": "BELLO", "long": -75.5667, "lat": 6.3333, "cases": 4429}, {"city": "ITAGUI", "long": -75.6167, "lat": 6.1667, "cases": 3576}, {"city": "ENVIGADO", "long": -75.5667, "lat": 6.1667, "cases": 2623}, {"city": "TURBO", "long": -76.7333, "lat": 8.1, "cases": 684}, {"city": "RIONEGRO", "long": -75.3743, "lat": 6.1535, "cases": 1265}, {"city": "APARTADO", "long": -76.6333, "lat": 7.8833, "cases": 1280}, {"city": "SABANETA", "long": -75.6, "lat": 6.15, "cases": 858}, {"city": "CAUCASIA", "long": -75.2, "lat": 7.9833, "cases": 843}, {"city": "CHIGORODO", "long": -76.6808, "lat": 7.6675, "cases": 398}, {"city": "CALDAS", "long": -75.638, "lat": 6.09, "cases": 1157}, {"city": "COPACABANA", "long": -75.5, "lat": 6.3333, "cases": 1184}, {"city": "LA ESTRELLA", "long": -75.6667, "lat": 6.1667, "cases": 873}, {"city": "NECOCLI", "long": -76.7833, "lat": 8.4167, "cases": 179}, {"city": "MARINILLA", "long": -75.3347, "lat": 6.1738, "cases": 201}, {"city": "LA CEJA", "long": -75.4317, "lat": 6.0306, "cases": 226}, {"city": "GIRARDOTA", "long": -75.4473, "lat": 6.3764, "cases": 601}, {"city": "EL BAGRE", "long": -74.8119, "lat": 7.5942, "cases": 165}, {"city": "GUARNE", "long": -75.4427, "lat": 6.28, "cases": 354}, {"city": "CARMEN DE VIBORAL", "long": -75.3333, "lat": 6.0833, "cases": 447}, {"city": "CAREPA", "long": -76.6553, "lat": 7.7578, "cases": 271}, {"city": "URRAO", "long": -76.1342, "lat": 6.3156, "cases": 147}, {"city": "ARBOLETES", "long": -76.4283, "lat": 8.8517, "cases": 92}, {"city": "ANDES", "long": -75.9167, "lat": 5.5833, "cases": 517}, {"city": "CACERES", "long": -75.3333, "lat": 7.6667, "cases": 88}, {"city": "SEGOVIA", "long": -74.7017, "lat": 7.0781, "cases": 278}, {"city": "PUERTO BERRIO", "long": -74.4025, "lat": 6.49, "cases": 551}, {"city": "TARAZA", "long": -75.4028, "lat": 7.5881, "cases": 122}, {"city": "SANTA ROSA DE OSOS", "long": -75.4667, "lat": 6.65, "cases": 236}, {"city": "SONSON", "long": -75.3108, "lat": 5.7097, "cases": 219}, {"city": "SAN PEDRO DE URABA", "long": -76.3833, "lat": 8.2833, "cases": 70}, {"city": "REMEDIOS", "long": -74.6939, "lat": 7.0275, "cases": 166}, {"city": "AMAGA", "long": -75.7, "lat": 6.05, "cases": 229}, {"city": "CIUDAD BOLIVAR", "long": -76.0333, "lat": 5.85, "cases": 209}, {"city": "SAN JUAN DE URABA", "long": -76.5333, "lat": 8.7667, "cases": 42}, {"city": "NECHI", "long": -74.7833, "lat": 8.1, "cases": 40}, {"city": "YOLOMBO", "long": -75.0122, "lat": 6.5978, "cases": 92}, {"city": "ZARAGOZA", "long": -74.871, "lat": 7.494, "cases": 148}, {"city": "ITUANGO", "long": -75.75, "lat": 7.1667, "cases": 94}, {"city": "DABEIBA", "long": -76.25, "lat": 7.0, "cases": 62}, {"city": "AMALFI", "long": -75.0833, "lat": 6.9167, "cases": 172}, {"city": "MUTATA", "long": -76.4358, "lat": 7.2442, "cases": 69}, {"city": "PUERTO TRIUNFO", "long": -74.65, "lat": 5.8667, "cases": 142}, {"city": "SANTA BARBARA", "long": -75.5661, "lat": 5.8747, "cases": 185}, {"city": "FREDONIA", "long": -75.6667, "lat": 5.9167, "cases": 246}, {"city": "FRONTINO", "long": -76.1333, "lat": 6.7833, "cases": 106}, {"city": "SAN VICENTE", "long": -75.3322, "lat": 6.2819, "cases": 155}, {"city": "SALGAR", "long": -75.9753, "lat": 5.9617, "cases": 116}, {"city": "ABEJORRAL", "long": -75.4281, "lat": 5.7894, "cases": 85}, {"city": "YONDO", "long": -73.9167, "lat": 7.0, "cases": 140}, {"city": "BETULIA", "long": -75.9839, "lat": 6.1122, "cases": 209}, {"city": "RETIRO", "long": -75.5025, "lat": 6.0572, "cases": 111}, {"city": "SAN ROQUE", "long": -75.0197, "lat": 6.4853, "cases": 114}, {"city": "ANORI", "long": -75.1458, "lat": 7.0736, "cases": 112}, {"city": "TAMESIS", "long": -75.7167, "lat": 5.6667, "cases": 92}, {"city": "COCORNA", "long": -75.1853, "lat": 6.0569, "cases": 179}, {"city": "SOPETRAN", "long": -75.7433, "lat": 6.5017, "cases": 70}, {"city": "TITIRIBI", "long": -75.8, "lat": 6.0667, "cases": 76}, {"city": "JARDIN", "long": -75.8194, "lat": 5.5986, "cases": 61}, {"city": "CANASGORDAS", "long": -76.0258, "lat": 6.7497, "cases": 44}, {"city": "SAN JERONIMO", "long": -75.7278, "lat": 6.4417, "cases": 53}, {"city": "SAN RAFAEL", "long": -75.0314, "lat": 6.2975, "cases": 79}, {"city": "PUERTO NARE", "long": -74.5867, "lat": 6.1917, "cases": 90}, {"city": "EBEJICO", "long": -75.7667, "lat": 6.3333, "cases": 70}, {"city": "JERICO", "long": -75.7833, "lat": 5.7833, "cases": 161}, {"city": "CISNEROS", "long": -75.0886, "lat": 6.5383, "cases": 137}, {"city": "SANTO DOMINGO", "long": -75.1658, "lat": 6.4708, "cases": 64}, {"city": "ANGOSTURA", "long": -75.3333, "lat": 6.8667, "cases": 87}, {"city": "VENECIA", "long": -75.75, "lat": 5.9167, "cases": 144}, {"city": "VEGACHI", "long": -74.7994, "lat": 6.7731, "cases": 67}, {"city": "BETANIA", "long": -75.9667, "lat": 5.75, "cases": 88}, {"city": "GUATAPE", "long": -75.1667, "lat": 6.2333, "cases": 62}, {"city": "CAMPAMENTO", "long": -75.2964, "lat": 6.9789, "cases": 64}, {"city": "ANGELOPOLIS", "long": -75.7, "lat": 6.1333, "cases": 85}, {"city": "ENTRERRIOS", "long": -75.5167, "lat": 6.5667, "cases": 51}, {"city": "BRICENO", "long": -75.55, "lat": 7.1111, "cases": 81}, {"city": "NARINO", "long": -75.1764, "lat": 5.6092, "cases": 98}, {"city": "YALI", "long": -74.8411, "lat": 6.6767, "cases": 46}], "VALLE": [{"city": "CALI", "long": -76.5222, "lat": 3.4206, "cases": 18188}, {"city": "BUENAVENTURA", "long": -77.0267, "lat": 3.8772, "cases": 2557}, {"city": "PALMIRA", "long": -76.25, "lat": 3.5833, "cases": 2329}, {"city": "ZARZAL", "long": -76.0772, "lat": 4.3983, "cases": 624}, {"city": "TULUA", "long": -76.2, "lat": 4.0833, "cases": 2088}, {"city": "CARTAGO", "long": -75.9167, "lat": 4.7, "cases": 1769}, {"city": "GUADALAJARA DE BUGA", "long": -76.3019, "lat": 3.9, "cases": 2718}, {"city": "JAMUNDI", "long": -76.55, "lat": 3.2667, "cases": 1145}, {"city": "YUMBO", "long": -76.4958, "lat": 3.585, "cases": 1321}, {"city": "FLORIDA", "long": -76.2386, "lat": 3.3275, "cases": 688}, {"city": "PRADERA", "long": -76.1667, "lat": 3.4167, "cases": 476}, {"city": "EL CERRITO", "long": -76.1667, "lat": 3.6667, "cases": 767}, {"city": "ROLDANILLO", "long": -76.15, "lat": 4.4167, "cases": 441}, {"city": "SEVILLA", "long": -75.9361, "lat": 4.2689, "cases": 533}, {"city": "DAGUA", "long": -76.7, "lat": 3.6667, "cases": 557}, {"city": "GUACARI", "long": -76.3333, "lat": 3.7667, "cases": 405}, {"city": "CAICEDONIA", "long": -75.8333, "lat": 4.3333, "cases": 404}, {"city": "ALCALA", "long": -75.75, "lat": 4.6667, "cases": 95}, {"city": "GINEBRA", "long": -76.1667, "lat": 3.75, "cases": 259}, {"city": "BUGALAGRANDE", "long": -76.1667, "lat": 4.2167, "cases": 276}, {"city": "ANSERMANUEVO", "long": -76.0, "lat": 4.8, "cases": 106}, {"city": "ANDALUCIA", "long": -76.1667, "lat": 4.1667, "cases": 238}, {"city": "TRUJILLO", "long": -76.3333, "lat": 4.25, "cases": 198}, {"city": "TORO", "long": -76.0814, "lat": 4.6117, "cases": 59}, {"city": "YOTOCO", "long": -76.3833, "lat": 3.8667, "cases": 237}, {"city": "OBANDO", "long": -75.9167, "lat": 4.5833, "cases": 73}, {"city": "RIOFRIO", "long": -76.2878, "lat": 4.1561, "cases": 171}, {"city": "LA VICTORIA", "long": -76.0364, "lat": 4.5214, "cases": 181}, {"city": "EL AGUILA", "long": -76.0833, "lat": 4.9167, "cases": 37}, {"city": "VIJES", "long": -76.45, "lat": 3.7, "cases": 77}, {"city": "EL CAIRO", "long": -76.25, "lat": 4.75, "cases": 49}, {"city": "EL DOVIO", "long": -76.2333, "lat": 4.5167, "cases": 64}], "ATLANTICO": [{"city": "BARRANQUILLA", "long": -74.8019, "lat": 10.9833, "cases": 7546}, {"city": "SOLEDAD", "long": -74.75, "lat": 10.9167, "cases": 4319}, {"city": "MALAMBO", "long": -74.75, "lat": 10.85, "cases": 725}, {"city": "BARANOA", "long": -74.9167, "lat": 10.8, "cases": 182}, {"city": "GALAPA", "long": -74.8333, "lat": 10.9167, "cases": 263}, {"city": "PUERTO COLOMBIA", "long": -74.8833, "lat": 11.0167, "cases": 354}, {"city": "SABANAGRANDE", "long": -74.75, "lat": 10.8, "cases": 93}, {"city": "SANTO TOMAS", "long": -74.9167, "lat": 10.7667, "cases": 65}, {"city": "PALMAR DE VARELA", "long": -74.75, "lat": 10.75, "cases": 54}, {"city": "LURUACO", "long": -75.1417, "lat": 10.6083, "cases": 124}, {"city": "REPELON", "long": -75.1333, "lat": 10.55, "cases": 63}, {"city": "POLONUEVO", "long": -74.8667, "lat": 10.7833, "cases": 29}, {"city": "CAMPO DE LA CRUZ", "long": -74.8814, "lat": 10.3778, "cases": 30}, {"city": "PONEDERA", "long": -74.75, "lat": 10.65, "cases": 43}, {"city": "JUAN DE ACOSTA", "long": -75.0333, "lat": 10.8333, "cases": 26}, {"city": "MANATI", "long": -74.9597, "lat": 10.445, "cases": 39}, {"city": "SANTA LUCIA", "long": -74.95, "lat": 10.3167, "cases": 14}, {"city": "TUBARA", "long": -74.9833, "lat": 10.8667, "cases": 36}, {"city": "SUAN", "long": -74.8833, "lat": 10.3333, "cases": 12}, {"city": "USIACURI", "long": -74.9833, "lat": 10.75, "cases": 16}], "BOLIVAR": [{"city": "CARTAGENA", "long": -75.5, "lat": 10.4, "cases": 7598}, {"city": "MAGANGUE", "long": -74.7667, "lat": 9.25, "cases": 1554}, {"city": "TURBACO", "long": -75.3333, "lat": 10.35, "cases": 585}, {"city": "ARJONA", "long": -75.3461, "lat": 10.2586, "cases": 341}, {"city": "TURBANA", "long": -75.45, "lat": 10.2833, "cases": 74}, {"city": "EL CARMEN DE BOLIVAR", "long": -75.1333, "lat": 9.7167, "cases": 983}, {"city": "MARIA LA BAJA", "long": -75.3333, "lat": 10.0, "cases": 228}, {"city": "SANTA ROSA DEL SUR", "long": -74.05, "lat": 7.9667, "cases": 120}, {"city": "SAN JUAN NEPOMUCENO", "long": -75.0833, "lat": 9.95, "cases": 311}, {"city": "MAHATES", "long": -75.1833, "lat": 10.2333, "cases": 57}, {"city": "PINILLOS", "long": -74.4667, "lat": 8.9167, "cases": 19}, {"city": "SANTA ROSA", "long": -75.3686, "lat": 10.4456, "cases": 260}, {"city": "ACHI", "long": -74.55, "lat": 8.5667, "cases": 27}, {"city": "TIQUISIO", "long": -74.2667, "lat": 8.5667, "cases": 27}, {"city": "SAN JACINTO", "long": -75.1219, "lat": 9.8311, "cases": 148}, {"city": "MONTECRISTO", "long": -74.4756, "lat": 8.2994, "cases": 10}, {"city": "SIMITI", "long": -73.95, "lat": 7.9667, "cases": 133}, {"city": "SAN ESTANISLAO", "long": -75.15, "lat": 10.4, "cases": 72}, {"city": "SAN MARTIN DE LOBA", "long": -73.9167, "lat": 8.8333, "cases": 83}, {"city": "BARRANCO DE LOBA", "long": -74.1167, "lat": 8.95, "cases": 37}, {"city": "SANTA CATALINA", "long": -75.2878, "lat": 10.6039, "cases": 114}, {"city": "CLEMENCIA", "long": -75.3333, "lat": 10.5833, "cases": 115}, {"city": "ALTOS DEL ROSARIO", "long": -74.1667, "lat": 8.8, "cases": 12}, {"city": "SAN JACINTO DEL CAUCA", "long": -74.7167, "lat": 8.25, "cases": 2}, {"city": "CICUCO", "long": -74.65, "lat": 9.2667, "cases": 58}, {"city": "HATILLO DE LOBA", "long": -74.0808, "lat": 8.9586, "cases": 26}, {"city": "ZAMBRANO", "long": -74.8333, "lat": 9.75, "cases": 44}, {"city": "TALAIGUA NUEVO", "long": -74.5686, "lat": 9.3069, "cases": 31}, {"city": "REGIDOR", "long": -73.8333, "lat": 8.6667, "cases": 11}, {"city": "MARGARITA", "long": -74.2, "lat": 9.0833, "cases": 10}, {"city": "NOROSI", "long": -74.0378, "lat": 8.5261, "cases": 2}, {"city": "SAN FERNANDO", "long": -74.5339, "lat": 9.2797, "cases": 15}], "SANTANDER": [{"city": "BUCARAMANGA", "long": -73.0, "lat": 7.1333, "cases": 10066}, {"city": "FLORIDABLANCA", "long": -73.0667, "lat": 7.2167, "cases": 4966}, {"city": "BARRANCABERMEJA", "long": -73.85, "lat": 7.0667, "cases": 3875}, {"city": "GIRON", "long": -73.1681, "lat": 7.0731, "cases": 4465}, {"city": "PIEDECUESTA", "long": -73.0, "lat": 7.0833, "cases": 2965}, {"city": "SAN GIL", "long": -73.135, "lat": 6.5592, "cases": 1171}, {"city": "CIMITARRA", "long": -73.95, "lat": 6.3167, "cases": 555}, {"city": "SAN VICENTE DE CHUCURI", "long": -73.4167, "lat": 6.8833, "cases": 401}, {"city": "PUERTO WILCHES", "long": -73.9, "lat": 7.35, "cases": 252}, {"city": "SOCORRO", "long": -73.2, "lat": 6.5333, "cases": 481}, {"city": "MALAGA", "long": -72.6667, "lat": 6.7833, "cases": 234}, {"city": "VELEZ", "long": -73.6763, "lat": 6.0103, "cases": 278}, {"city": "SABANA DE TORRES", "long": -73.5, "lat": 7.4, "cases": 505}, {"city": "EL CARMEN DE CHUCURI", "long": -73.5111, "lat": 6.6981, "cases": 151}, {"city": "LANDAZURI", "long": -73.8114, "lat": 6.2181, "cases": 84}, {"city": "LOS SANTOS", "long": -73.0833, "lat": 6.9167, "cases": 85}, {"city": "CURITI", "long": -73.0, "lat": 6.6667, "cases": 120}, {"city": "OIBA", "long": -73.3, "lat": 6.2667, "cases": 141}, {"city": "PUENTE NACIONAL", "long": -73.6833, "lat": 5.8833, "cases": 205}, {"city": "EL PLAYON", "long": -73.2081, "lat": 7.4767, "cases": 190}, {"city": "MOGOTES", "long": -72.9667, "lat": 6.4833, "cases": 156}, {"city": "CHARALA", "long": -73.0833, "lat": 6.25, "cases": 135}, {"city": "SUAITA", "long": -73.4406, "lat": 6.1019, "cases": 124}, {"city": "ZAPATOCA", "long": -73.2667, "lat": 6.8167, "cases": 81}, {"city": "LA BELLEZA", "long": -73.9683, "lat": 5.8614, "cases": 58}], "HUILA": [{"city": "PALERMO", "long": -75.4375, "lat": 2.8917, "cases": 189}, {"city": "NEIVA", "long": -75.2809, "lat": 2.9345, "cases": 6674}, {"city": "PITALITO", "long": -76.0419, "lat": 1.8989, "cases": 2219}, {"city": "GARZON", "long": -75.6578, "lat": 2.1819, "cases": 1167}, {"city": "LA PLATA", "long": -75.9075, "lat": 2.39, "cases": 737}, {"city": "ACEVEDO", "long": -75.8964, "lat": 1.8192, "cases": 421}, {"city": "GIGANTE", "long": -75.5461, "lat": 2.3867, "cases": 262}, {"city": "CAMPOALEGRE", "long": -75.3256, "lat": 2.6867, "cases": 375}, {"city": "SAN AGUSTIN", "long": -76.2833, "lat": 1.9, "cases": 626}, {"city": "AIPE", "long": -75.2333, "lat": 3.2167, "cases": 194}, {"city": "ISNOS", "long": -76.2333, "lat": 1.9333, "cases": 373}, {"city": "ALGECIRAS", "long": -75.3167, "lat": 2.5333, "cases": 179}, {"city": "GUADALUPE", "long": -75.7572, "lat": 2.025, "cases": 264}, {"city": "RIVERA", "long": -75.2589, "lat": 2.7853, "cases": 260}, {"city": "SUAZA", "long": -75.8167, "lat": 1.9833, "cases": 108}, {"city": "TIMANA", "long": -75.95, "lat": 1.9833, "cases": 251}, {"city": "TARQUI", "long": -75.8231, "lat": 2.1106, "cases": 97}, {"city": "LA ARGENTINA", "long": -75.98, "lat": 2.1961, "cases": 62}, {"city": "OPORAPA", "long": -75.9667, "lat": 2.05, "cases": 105}, {"city": "TELLO", "long": -75.1333, "lat": 3.0667, "cases": 164}, {"city": "SANTA MARIA", "long": -75.65, "lat": 2.95, "cases": 104}, {"city": "SALADOBLANCO", "long": -76.05, "lat": 2.0167, "cases": 69}, {"city": "TESALIA", "long": -75.7333, "lat": 2.4833, "cases": 112}, {"city": "IQUIRA", "long": -75.65, "lat": 2.65, "cases": 77}, {"city": "YAGUARA", "long": -75.5186, "lat": 2.6661, "cases": 143}, {"city": "TERUEL", "long": -75.5667, "lat": 2.75, "cases": 98}], "NORTE": [{"city": "CUCUTA", "long": -72.5039, "lat": 7.8942, "cases": 6097}, {"city": "OCANA", "long": -73.35, "lat": 8.2333, "cases": 1833}, {"city": "LOS PATIOS", "long": -72.5167, "lat": 7.8333, "cases": 703}, {"city": "VILLA DEL ROSARIO", "long": -72.4742, "lat": 7.8339, "cases": 722}, {"city": "PAMPLONA", "long": -72.6525, "lat": 7.3781, "cases": 503}, {"city": "ABREGO", "long": -73.2, "lat": 8.0, "cases": 214}, {"city": "TIBU", "long": -72.7333, "lat": 8.65, "cases": 536}, {"city": "EL ZULIA", "long": -72.6, "lat": 7.9333, "cases": 171}, {"city": "TEORAMA", "long": -73.2864, "lat": 8.4353, "cases": 52}, {"city": "SARDINATA", "long": -72.8, "lat": 8.0833, "cases": 121}, {"city": "TOLEDO", "long": -72.4875, "lat": 7.3131, "cases": 64}, {"city": "CHINACOTA", "long": -72.6, "lat": 7.6167, "cases": 121}, {"city": "EL CARMEN", "long": -73.4508, "lat": 8.5128, "cases": 46}, {"city": "LA ESPERANZA", "long": -73.3358, "lat": 7.6392, "cases": 60}, {"city": "EL TARRA", "long": -73.0944, "lat": 8.5756, "cases": 30}, {"city": "CACHIRA", "long": -73.1667, "lat": 7.75, "cases": 15}, {"city": "CHITAGA", "long": -72.6667, "lat": 7.1333, "cases": 98}, {"city": "PUERTO SANTANDER", "long": -72.4075, "lat": 8.3636, "cases": 55}, {"city": "SAN CALIXTO", "long": -73.2167, "lat": 8.4, "cases": 5}, {"city": "HACARI", "long": -73.15, "lat": 8.3167, "cases": 11}, {"city": "ARBOLEDAS", "long": -72.75, "lat": 7.6667, "cases": 42}], "META": [{"city": "VILLAVICENCIO", "long": -73.6333, "lat": 4.15, "cases": 8334}, {"city": "ACACIAS", "long": -73.7597, "lat": 3.9878, "cases": 1477}, {"city": "PUERTO GAITAN", "long": -72.0825, "lat": 4.3142, "cases": 302}, {"city": "LA MACARENA", "long": -73.7847, "lat": 2.1828, "cases": 118}, {"city": "PUERTO LOPEZ", "long": -72.9667, "lat": 4.0833, "cases": 325}, {"city": "VISTAHERMOSA", "long": -73.7514, "lat": 3.1239, "cases": 199}, {"city": "PUERTO CONCORDIA", "long": -72.7667, "lat": 2.6833, "cases": 40}, {"city": "CUMARAL", "long": -73.4864, "lat": 4.2694, "cases": 247}, {"city": "CASTILLA LA NUEVA", "long": -73.6833, "lat": 3.8333, "cases": 127}, {"city": "FUENTE DE ORO", "long": -73.6167, "lat": 3.4667, "cases": 118}, {"city": "SAN CARLOS DE GUAROA", "long": -73.2425, "lat": 3.7111, "cases": 150}, {"city": "HATO COROZAL", "long": -73.75, "lat": 3.1833, "cases": 105}, {"city": "LEJANIAS", "long": -74.0232, "lat": 3.5268, "cases": 115}, {"city": "MESETAS", "long": -74.0447, "lat": 3.3781, "cases": 91}, {"city": "PUERTO LLERAS", "long": -73.375, "lat": 3.2694, "cases": 116}, {"city": "SAN JUAN DE ARAMA", "long": -73.8767, "lat": 3.3736, "cases": 77}], "RISARALDA": [{"city": "PEREIRA", "long": -75.6946, "lat": 4.8143, "cases": 6832}, {"city": "DOSQUEBRADAS", "long": -75.6833, "lat": 4.8333, "cases": 3429}, {"city": "SANTA ROSA DE CABAL", "long": -75.6167, "lat": 4.8667, "cases": 1337}, {"city": "QUINCHIA", "long": -75.7296, "lat": 5.3379, "cases": 147}, {"city": "LA VIRGINIA", "long": -75.8333, "lat": 4.9167, "cases": 624}, {"city": "MARSELLA", "long": -75.75, "lat": 4.9167, "cases": 162}, {"city": "BELEN DE UMBRIA", "long": -75.8667, "lat": 5.2, "cases": 193}, {"city": "MISTRATO", "long": -75.8833, "lat": 5.3, "cases": 39}, {"city": "GUATICA", "long": -75.8, "lat": 5.3167, "cases": 101}, {"city": "PUEBLO RICO", "long": -76.1667, "lat": 5.25, "cases": 87}, {"city": "APIA", "long": -75.95, "lat": 5.1, "cases": 117}, {"city": "LA CELIA", "long": -76.0039, "lat": 5.0019, "cases": 28}], "CESAR": [{"city": "VALLEDUPAR", "long": -73.25, "lat": 10.4833, "cases": 2181}, {"city": "AGUACHICA", "long": -73.6333, "lat": 8.3167, "cases": 1046}, {"city": "LA JAGUA DE IBIRICO", "long": -73.3333, "lat": 9.5667, "cases": 67}, {"city": "AGUSTIN CODAZZI", "long": -73.2369, "lat": 10.0367, "cases": 232}, {"city": "BOSCONIA", "long": -73.8903, "lat": 9.9761, "cases": 86}, {"city": "CHIMICHAGUA", "long": -73.8167, "lat": 9.25, "cases": 37}, {"city": "EL COPEY", "long": -73.9667, "lat": 10.15, "cases": 82}, {"city": "PUEBLO BELLO", "long": -73.5833, "lat": 10.4167, "cases": 20}, {"city": "CHIRIGUANA", "long": -73.6, "lat": 9.3667, "cases": 65}, {"city": "SAN ALBERTO", "long": -73.3892, "lat": 7.7525, "cases": 112}, {"city": "EL PASO", "long": -73.7519, "lat": 9.6622, "cases": 65}, {"city": "CURUMANI", "long": -73.55, "lat": 9.2, "cases": 111}, {"city": "PAILITAS", "long": -73.6333, "lat": 8.9667, "cases": 62}, {"city": "BECERRIL", "long": -73.2833, "lat": 9.7, "cases": 26}, {"city": "SAN DIEGO", "long": -73.1825, "lat": 10.3375, "cases": 37}, {"city": "ASTREA", "long": -73.9833, "lat": 9.5, "cases": 25}, {"city": "PELAYA", "long": -73.6667, "lat": 8.6833, "cases": 33}, {"city": "RIO DE ORO", "long": -73.3872, "lat": 8.2917, "cases": 94}, {"city": "GAMARRA", "long": -73.6667, "lat": 8.3333, "cases": 43}, {"city": "GONZALEZ", "long": -73.3333, "lat": 8.4, "cases": 20}], "TOLIMA": [{"city": "IBAGUE", "long": -75.2333, "lat": 4.4333, "cases": 6728}, {"city": "ESPINAL", "long": -74.8333, "lat": 4.2, "cases": 768}, {"city": "CHAPARRAL", "long": -75.5833, "lat": 3.75, "cases": 504}, {"city": "ORTEGA", "long": -75.25, "lat": 3.9167, "cases": 192}, {"city": "LIBANO", "long": -75.1667, "lat": 4.9167, "cases": 243}, {"city": "MELGAR", "long": -74.6428, "lat": 4.2039, "cases": 434}, {"city": "SAN SEBASTIAN DE MARIQUITA", "long": -74.9167, "lat": 5.25, "cases": 488}, {"city": "GUAMO", "long": -74.9167, "lat": 4.0833, "cases": 275}, {"city": "PLANADAS", "long": -75.6444, "lat": 3.1964, "cases": 78}, {"city": "FRESNO", "long": -75.0403, "lat": 5.1556, "cases": 107}, {"city": "PURIFICACION", "long": -74.9333, "lat": 3.8667, "cases": 142}, {"city": "FLANDES", "long": -74.8, "lat": 4.2833, "cases": 326}, {"city": "COYAIMA", "long": -75.0833, "lat": 3.8333, "cases": 92}, {"city": "RIOBLANCO", "long": -75.8333, "lat": 3.5, "cases": 45}, {"city": "HONDA", "long": -74.7417, "lat": 5.2042, "cases": 224}, {"city": "NATAGAIMA", "long": -75.0833, "lat": 3.5833, "cases": 106}, {"city": "ROVIRA", "long": -75.3333, "lat": 4.25, "cases": 231}, {"city": "VENADILLO", "long": -74.9167, "lat": 4.75, "cases": 69}, {"city": "ANZOATEGUI", "long": -75.0972, "lat": 4.6339, "cases": 39}, {"city": "CAJAMARCA", "long": -75.5, "lat": 4.4167, "cases": 247}, {"city": "LERIDA", "long": -74.9167, "lat": 4.9, "cases": 128}, {"city": "SALDANA", "long": -75.0203, "lat": 3.9347, "cases": 199}, {"city": "ATACO", "long": -75.3833, "lat": 3.6, "cases": 45}, {"city": "ICONONZO", "long": -74.5333, "lat": 4.1833, "cases": 168}, {"city": "VILLAHERMOSA", "long": -75.1667, "lat": 5.0, "cases": 26}, {"city": "COELLO", "long": -74.9167, "lat": 4.3333, "cases": 53}, {"city": "CUNDAY", "long": -74.6667, "lat": 4.0833, "cases": 75}, {"city": "PALOCABILDO", "long": -75.0333, "lat": 5.1333, "cases": 28}, {"city": "FALAN", "long": -74.95, "lat": 5.1333, "cases": 40}, {"city": "CARMEN DE APICALA", "long": -74.7333, "lat": 4.15, "cases": 93}, {"city": "ALVARADO", "long": -74.95, "lat": 4.5667, "cases": 93}], "CUNDINAMARCA": [{"city": "SOACHA", "long": -74.2214, "lat": 4.5872, "cases": 3776}, {"city": "ZIPAQUIRA", "long": -74.0, "lat": 5.0333, "cases": 1579}, {"city": "FUSAGASUGA", "long": -74.3618, "lat": 4.3452, "cases": 1168}, {"city": "GIRARDOT", "long": -74.8017, "lat": 4.305, "cases": 1564}, {"city": "FACATATIVA", "long": -74.3667, "lat": 4.8167, "cases": 1430}, {"city": "MADRID", "long": -74.2683, "lat": 4.7344, "cases": 631}, {"city": "CHIA", "long": -74.05, "lat": 4.85, "cases": 886}, {"city": "FUNZA", "long": -74.2167, "lat": 4.7167, "cases": 421}, {"city": "CAJICA", "long": -74.0333, "lat": 4.9167, "cases": 262}, {"city": "VILLETA", "long": -74.4738, "lat": 5.0083, "cases": 314}, {"city": "GUADUAS", "long": -74.5981, "lat": 5.0694, "cases": 162}, {"city": "VILLA DE SAN DIEGO DE UBATE", "long": -73.8144, "lat": 5.3072, "cases": 454}, {"city": "SIBATE", "long": -74.2594, "lat": 4.4908, "cases": 146}, {"city": "TOCANCIPA", "long": -73.9136, "lat": 4.9657, "cases": 464}, {"city": "LA MESA", "long": -74.4625, "lat": 4.6303, "cases": 214}, {"city": "TABIO", "long": -74.0983, "lat": 4.9158, "cases": 73}, {"city": "SOPO", "long": -73.9333, "lat": 4.9167, "cases": 105}, {"city": "LA CALERA", "long": -73.92, "lat": 4.7531, "cases": 221}, {"city": "COTA", "long": -74.1, "lat": 4.8167, "cases": 124}, {"city": "CHOCONTA", "long": -73.6825, "lat": 5.1467, "cases": 115}, {"city": "PACHO", "long": -74.1583, "lat": 5.1306, "cases": 160}, {"city": "COGUA", "long": -73.9833, "lat": 5.0667, "cases": 368}, {"city": "EL COLEGIO", "long": -74.4425, "lat": 4.5808, "cases": 190}, {"city": "SILVANIA", "long": -74.3881, "lat": 4.4033, "cases": 169}, {"city": "VILLAPINZON", "long": -73.6, "lat": 5.2167, "cases": 125}, {"city": "TENJO", "long": -74.1667, "lat": 4.9167, "cases": 110}, {"city": "EL ROSAL", "long": -74.2628, "lat": 4.8519, "cases": 200}, {"city": "TOCAIMA", "long": -74.6667, "lat": 4.5, "cases": 121}, {"city": "GACHANCIPA", "long": -73.8731, "lat": 4.9908, "cases": 202}, {"city": "SUESCA", "long": -73.8, "lat": 5.1, "cases": 47}, {"city": "CAQUEZA", "long": -73.9478, "lat": 4.4053, "cases": 181}, {"city": "SUBACHOQUE", "long": -74.1736, "lat": 4.9281, "cases": 122}, {"city": "GUASCA", "long": -73.8772, "lat": 4.8658, "cases": 94}, {"city": "PUERTO SALGAR", "long": -74.5833, "lat": 5.5, "cases": 138}, {"city": "ANAPOIMA", "long": -74.5361, "lat": 4.5503, "cases": 88}, {"city": "SESQUILE", "long": -73.7972, "lat": 5.0453, "cases": 46}, {"city": "NEMOCON", "long": -73.8833, "lat": 5.05, "cases": 122}, {"city": "SIMIJACA", "long": -73.8519, "lat": 5.5019, "cases": 61}, {"city": "SAN ANTONIO DEL TEQUENDAMA", "long": -74.3522, "lat": 4.6328, "cases": 80}, {"city": "ANOLAIMA", "long": -74.464, "lat": 4.7617, "cases": 23}, {"city": "VIOTA", "long": -74.5239, "lat": 4.4381, "cases": 30}, {"city": "SUSA", "long": -73.814, "lat": 5.4528, "cases": 27}, {"city": "ARBELAEZ", "long": -74.4151, "lat": 4.2725, "cases": 119}, {"city": "FOMEQUE", "long": -73.8936, "lat": 4.4847, "cases": 90}, {"city": "PASCA", "long": -74.3008, "lat": 4.3075, "cases": 71}, {"city": "GUACHETA", "long": -73.6856, "lat": 5.3856, "cases": 66}, {"city": "GACHETA", "long": -73.636, "lat": 4.8176, "cases": 52}, {"city": "AGUA DE DIOS", "long": -74.6739, "lat": 4.3781, "cases": 61}, {"city": "LA PALMA", "long": -74.3897, "lat": 5.3606, "cases": 44}, {"city": "YACOPI", "long": -74.3333, "lat": 5.4667, "cases": 28}, {"city": "CHOACHI", "long": -73.9236, "lat": 4.5297, "cases": 79}, {"city": "UBALA", "long": -73.5347, "lat": 4.7439, "cases": 39}, {"city": "LENGUAZAQUE", "long": -73.7061, "lat": 5.3069, "cases": 44}, {"city": "CAPARRAPI", "long": -74.4917, "lat": 5.3442, "cases": 30}, {"city": "MEDINA", "long": -73.3494, "lat": 4.5092, "cases": 44}, {"city": "SASAIMA", "long": -74.4347, "lat": 4.965, "cases": 41}, {"city": "CACHIPAY", "long": -74.4375, "lat": 4.7308, "cases": 53}, {"city": "BOJACA", "long": -74.3422, "lat": 4.7336, "cases": 84}, {"city": "UNE", "long": -74.025, "lat": 4.4019, "cases": 49}, {"city": "CARMEN DE CARUPA", "long": -73.9053, "lat": 5.3503, "cases": 75}, {"city": "TENA", "long": -74.39, "lat": 4.6547, "cases": 100}, {"city": "TAUSA", "long": -73.8875, "lat": 5.1964, "cases": 47}, {"city": "JUNIN", "long": -73.8136, "lat": 4.7903, "cases": 35}], "MAGDALENA": [{"city": "SANTA MARTA", "long": -74.2053, "lat": 11.2419, "cases": 5554}, {"city": "CIENAGA", "long": -74.25, "lat": 11.0069, "cases": 897}, {"city": "FUNDACION", "long": -74.1867, "lat": 10.5214, "cases": 597}, {"city": "PLATO", "long": -74.7872, "lat": 9.7919, "cases": 223}, {"city": "EL BANCO", "long": -73.9747, "lat": 8.9983, "cases": 391}, {"city": "ARACATACA", "long": -74.1928, "lat": 10.5937, "cases": 244}, {"city": "PIVIJAY", "long": -74.6167, "lat": 10.4667, "cases": 125}, {"city": "PUEBLOVIEJO", "long": -74.2875, "lat": 10.9972, "cases": 94}, {"city": "SITIONUEVO", "long": -74.7167, "lat": 10.7833, "cases": 66}, {"city": "SANTA ANA", "long": -74.57, "lat": 9.319, "cases": 48}, {"city": "NUEVA GRANADA", "long": -74.3903, "lat": 9.8031, "cases": 21}, {"city": "EL RETEN", "long": -74.2667, "lat": 10.6167, "cases": 72}, {"city": "SAN SEBASTIAN DE BUENAVISTA", "long": -74.3556, "lat": 9.2403, "cases": 13}, {"city": "EL PINON", "long": -74.8231, "lat": 10.4039, "cases": 31}, {"city": "PIJINO DEL CARMEN", "long": -74.45, "lat": 9.3333, "cases": 19}, {"city": "TENERIFE", "long": -74.8589, "lat": 9.8989, "cases": 25}, {"city": "ALGARROBO", "long": -74.2667, "lat": 10.1, "cases": 66}, {"city": "SANTA BARBARA DE PINTO", "long": -74.7, "lat": 9.4333, "cases": 18}, {"city": "SAN ZENON", "long": -74.4992, "lat": 9.245, "cases": 18}], "CORDOBA": [{"city": "MONTERIA", "long": -75.8833, "lat": 8.75, "cases": 4207}, {"city": "SAHAGUN", "long": -75.45, "lat": 8.95, "cases": 894}, {"city": "MONTELIBANO", "long": -75.4208, "lat": 7.975, "cases": 561}, {"city": "CERETE", "long": -75.8, "lat": 8.8833, "cases": 622}, {"city": "TIERRALTA", "long": -76.0594, "lat": 8.1728, "cases": 379}, {"city": "PLANETA RICA", "long": -75.5819, "lat": 8.4089, "cases": 677}, {"city": "CIENAGA DE ORO", "long": -75.6167, "lat": 8.8833, "cases": 183}, {"city": "PUERTO LIBERTADOR", "long": -75.6733, "lat": 7.9067, "cases": 144}, {"city": "LORICA", "long": -75.816, "lat": 9.2419, "cases": 759}, {"city": "CHINU", "long": -75.3333, "lat": 9.0833, "cases": 419}, {"city": "SAN ANDRES DE SOTAVENTO", "long": -75.5, "lat": 9.15, "cases": 149}, {"city": "AYAPEL", "long": -75.15, "lat": 8.3167, "cases": 148}, {"city": "VALENCIA", "long": -76.1469, "lat": 8.2592, "cases": 61}, {"city": "SAN PELAYO", "long": -75.85, "lat": 8.9667, "cases": 121}, {"city": "PUEBLO NUEVO", "long": -75.5072, "lat": 8.5008, "cases": 150}, {"city": "TUCHIN", "long": -75.5553, "lat": 9.1858, "cases": 116}, {"city": "SAN BERNARDO DEL VIENTO", "long": -75.95, "lat": 9.35, "cases": 102}, {"city": "SAN ANTERO", "long": -75.75, "lat": 9.3833, "cases": 152}, {"city": "PUERTO ESCONDIDO", "long": -76.25, "lat": 8.95, "cases": 54}, {"city": "MONITOS", "long": -76.1325, "lat": 9.2503, "cases": 49}, {"city": "LOS CORDOBAS", "long": -76.3667, "lat": 8.9, "cases": 41}, {"city": "CANALETE", "long": -76.2411, "lat": 8.79, "cases": 38}, {"city": "COTORRA", "long": -75.8, "lat": 9.05, "cases": 70}, {"city": "MOMIL", "long": -75.6833, "lat": 9.2333, "cases": 88}, {"city": "LA APARTADA", "long": -75.3825, "lat": 8.1006, "cases": 98}, {"city": "CHIMA", "long": -75.6333, "lat": 9.15, "cases": 100}], "CALDAS": [{"city": "MANIZALES", "long": -75.55, "lat": 5.1, "cases": 3194}, {"city": "VILLAMARIA", "long": -75.5, "lat": 5.0, "cases": 381}, {"city": "CHINCHINA", "long": -75.6036, "lat": 4.9825, "cases": 890}, {"city": "ANSERMA", "long": -75.784, "lat": 5.2381, "cases": 337}, {"city": "NEIRA", "long": -75.5189, "lat": 5.1664, "cases": 129}, {"city": "SUPIA", "long": -75.65, "lat": 5.4667, "cases": 171}, {"city": "PENSILVANIA", "long": -75.0833, "lat": 5.5, "cases": 116}, {"city": "MANZANARES", "long": -75.1569, "lat": 5.2519, "cases": 165}, {"city": "AGUADAS", "long": -75.4667, "lat": 5.6167, "cases": 165}, {"city": "SALAMINA", "long": -75.49, "lat": 5.4083, "cases": 153}, {"city": "SAMANA", "long": -74.9167, "lat": 5.5833, "cases": 111}, {"city": "PACORA", "long": -75.4589, "lat": 5.5258, "cases": 60}, {"city": "VITERBO", "long": -75.8833, "lat": 5.0667, "cases": 90}, {"city": "MARQUETALIA", "long": -75.0, "lat": 5.3333, "cases": 48}, {"city": "ARANZAZU", "long": -75.45, "lat": 5.3, "cases": 93}, {"city": "FILADELFIA", "long": -75.6, "lat": 5.3, "cases": 33}, {"city": "RISARALDA", "long": -75.75, "lat": 5.1667, "cases": 90}], "NARINO": [{"city": "PASTO", "long": -77.2772, "lat": 1.2078, "cases": 6855}, {"city": "TUMACO", "long": -78.7647, "lat": 1.8067, "cases": 1167}, {"city": "IPIALES", "long": -77.6444, "lat": 0.8303, "cases": 1271}, {"city": "SAMANIEGO", "long": -77.6, "lat": 1.35, "cases": 86}, {"city": "EL CHARCO", "long": -78.1111, "lat": 2.4775, "cases": 32}, {"city": "CUMBAL", "long": -77.7908, "lat": 0.9078, "cases": 46}, {"city": "TUQUERRES", "long": -77.6167, "lat": 1.0833, "cases": 342}, {"city": "BARBACOAS", "long": -78.1397, "lat": 1.6717, "cases": 74}, {"city": "BUESACO", "long": -77.1667, "lat": 1.3833, "cases": 146}, {"city": "SANDONA", "long": -77.4667, "lat": 1.2833, "cases": 115}, {"city": "TAMINANGO", "long": -77.2833, "lat": 1.5667, "cases": 72}, {"city": "SAN BERNARDO", "long": -77.0467, "lat": 1.5108, "cases": 61}, {"city": "SAN LORENZO", "long": -77.2178, "lat": 1.5039, "cases": 28}, {"city": "GUACHUCAL", "long": -77.7333, "lat": 0.9667, "cases": 45}, {"city": "LA CRUZ", "long": -76.9742, "lat": 1.6047, "cases": 74}, {"city": "PUPIALES", "long": -77.65, "lat": 0.8667, "cases": 38}, {"city": "EL PENOL", "long": -75.2433, "lat": 6.2186, "cases": 17}, {"city": "CHACHAGUI", "long": -77.2835, "lat": 1.3605, "cases": 98}, {"city": "EL TAMBO", "long": -77.3981, "lat": 1.4131, "cases": 326}, {"city": "GUAITARILLA", "long": -77.5564, "lat": 1.1333, "cases": 55}, {"city": "YACUANQUER", "long": -77.4, "lat": 1.1167, "cases": 32}, {"city": "POTOSI", "long": -77.5728, "lat": 0.8081, "cases": 76}, {"city": "GENOVA", "long": -77.0194, "lat": 1.6442, "cases": 87}, {"city": "CONSACA", "long": -77.4667, "lat": 1.2, "cases": 50}, {"city": "LA FLORIDA", "long": -77.4106, "lat": 1.3017, "cases": 40}, {"city": "LINARES", "long": -77.5333, "lat": 1.35, "cases": 33}, {"city": "OSPINA", "long": -77.5664, "lat": 1.0581, "cases": 20}, {"city": "ILES", "long": -77.5167, "lat": 0.9667, "cases": 14}], "QUINDIO": [{"city": "ARMENIA", "long": -75.68, "lat": 4.53, "cases": 2602}, {"city": "CALARCA", "long": -75.65, "lat": 4.5333, "cases": 614}, {"city": "LA TEBAIDA", "long": -75.8, "lat": 4.45, "cases": 274}, {"city": "MONTENEGRO", "long": -75.7504, "lat": 4.5671, "cases": 222}, {"city": "QUIMBAYA", "long": -75.75, "lat": 4.6333, "cases": 233}, {"city": "CIRCASIA", "long": -75.6333, "lat": 4.6167, "cases": 170}, {"city": "FILANDIA", "long": -75.6333, "lat": 4.6667, "cases": 102}], "SUCRE": [{"city": "SINCELEJO", "long": -75.3961, "lat": 9.295, "cases": 4459}, {"city": "COROZAL", "long": -75.25, "lat": 9.3333, "cases": 925}, {"city": "SAN MARCOS", "long": -75.1347, "lat": 8.6611, "cases": 487}, {"city": "SAN ONOFRE", "long": -75.5333, "lat": 9.7333, "cases": 241}, {"city": "SAMPUES", "long": -75.3833, "lat": 9.1833, "cases": 517}, {"city": "SANTIAGO DE TOLU", "long": -75.5833, "lat": 9.5333, "cases": 586}, {"city": "SAN LUIS DE SINCE", "long": -75.15, "lat": 9.25, "cases": 301}, {"city": "MAJAGUAL", "long": -74.6667, "lat": 8.5, "cases": 74}, {"city": "SAN BENITO ABAD", "long": -75.0333, "lat": 8.9333, "cases": 97}, {"city": "LOS PALMITOS", "long": -75.2714, "lat": 9.3811, "cases": 183}, {"city": "GALERAS", "long": -75.05, "lat": 9.1667, "cases": 71}, {"city": "OVEJAS", "long": -75.1667, "lat": 9.5, "cases": 129}, {"city": "TOLU VIEJO", "long": -75.45, "lat": 9.45, "cases": 159}, {"city": "GUARANDA", "long": -74.5367, "lat": 8.4672, "cases": 48}, {"city": "MORROA", "long": -75.3167, "lat": 9.3333, "cases": 171}, {"city": "PALMITO", "long": -75.55, "lat": 9.3333, "cases": 43}, {"city": "SAN JUAN DE BETULIA", "long": -75.2456, "lat": 9.2756, "cases": 120}, {"city": "CAIMITO", "long": -75.1667, "lat": 8.8333, "cases": 36}, {"city": "COVENAS", "long": -75.7, "lat": 9.4167, "cases": 106}, {"city": "EL ROBLE", "long": -75.2, "lat": 9.1, "cases": 44}], "GUAJIRA": [{"city": "RIOHACHA", "long": -72.9069, "lat": 11.5442, "cases": 1989}, {"city": "MAICAO", "long": -72.2389, "lat": 11.3778, "cases": 693}, {"city": "URIBIA", "long": -72.2658, "lat": 11.7139, "cases": 65}, {"city": "MANAURE", "long": -72.4494, "lat": 11.7792, "cases": 49}, {"city": "SAN JUAN DEL CESAR", "long": -73.0, "lat": 10.7667, "cases": 214}, {"city": "BARRANCAS", "long": -72.75, "lat": 11.0, "cases": 102}, {"city": "DIBULLA", "long": -73.3, "lat": 11.2667, "cases": 142}, {"city": "FONSECA", "long": -72.8333, "lat": 10.8333, "cases": 225}, {"city": "HATONUEVO", "long": -72.7669, "lat": 11.0694, "cases": 46}, {"city": "ALBANIA", "long": -72.5856, "lat": 11.1597, "cases": 154}, {"city": "URUMITA", "long": -73.0167, "lat": 10.5667, "cases": 30}, {"city": "DISTRACCION", "long": -72.8833, "lat": 10.9, "cases": 44}], "CAQUETA": [{"city": "FLORENCIA", "long": -75.6128, "lat": 1.6139, "cases": 3178}, {"city": "SAN VICENTE DEL CAGUAN", "long": -74.7667, "lat": 2.1167, "cases": 442}, {"city": "CARTAGENA DEL CHAIRA", "long": -74.8333, "lat": 1.35, "cases": 184}, {"city": "SOLANO", "long": -75.2539, "lat": 0.6983, "cases": 51}, {"city": "LA MONTANITA", "long": -75.4361, "lat": 1.4792, "cases": 62}, {"city": "EL DONCELLO", "long": -75.2833, "lat": 1.6833, "cases": 110}, {"city": "EL PAUJIL", "long": -75.3319, "lat": 1.5644, "cases": 82}, {"city": "SAN JOSE DEL FRAGUA", "long": -75.9728, "lat": 1.3286, "cases": 81}, {"city": "BELEN DE LOS ANDAQUIES", "long": -75.8725, "lat": 1.4161, "cases": 79}, {"city": "SOLITA", "long": -75.65, "lat": 0.8667, "cases": 30}], "BOYACA": [{"city": "TUNJA", "long": -73.3667, "lat": 5.5333, "cases": 6584}, {"city": "DUITAMA", "long": -73.0167, "lat": 5.8333, "cases": 4337}, {"city": "SOGAMOSO", "long": -72.9208, "lat": 5.7167, "cases": 2575}, {"city": "CHIQUINQUIRA", "long": -73.75, "lat": 5.6333, "cases": 1757}, {"city": "PUERTO BOYACA", "long": -74.4167, "lat": 6.0, "cases": 634}, {"city": "PAIPA", "long": -73.15, "lat": 5.8333, "cases": 338}, {"city": "VILLA DE LEYVA", "long": -73.5333, "lat": 5.6333, "cases": 402}, {"city": "MONIQUIRA", "long": -73.5, "lat": 5.9167, "cases": 489}, {"city": "SAMACA", "long": -73.4833, "lat": 5.5, "cases": 330}, {"city": "GARAGOA", "long": -73.3667, "lat": 5.0833, "cases": 274}, {"city": "NOBSA", "long": -72.95, "lat": 5.7667, "cases": 248}, {"city": "AQUITANIA", "long": -72.8333, "lat": 5.5833, "cases": 184}, {"city": "VENTAQUEMADA", "long": -73.5, "lat": 5.4167, "cases": 260}, {"city": "COMBITA", "long": -73.25, "lat": 5.75, "cases": 164}, {"city": "TIBASOSA", "long": -72.9667, "lat": 5.8333, "cases": 275}, {"city": "RAQUIRA", "long": -73.6333, "lat": 5.5333, "cases": 100}, {"city": "SABOYA", "long": -73.7667, "lat": 5.7, "cases": 157}, {"city": "SANTA ROSA DE VITERBO", "long": -72.9833, "lat": 5.8833, "cases": 157}, {"city": "UMBITA", "long": -73.4667, "lat": 5.2167, "cases": 54}, {"city": "TOCA", "long": -73.2, "lat": 5.5667, "cases": 106}, {"city": "RAMIRIQUI", "long": -73.3333, "lat": 5.4, "cases": 349}, {"city": "GUATEQUE", "long": -73.4722, "lat": 5.0056, "cases": 256}, {"city": "SOCOTA", "long": -72.6333, "lat": 6.05, "cases": 40}, {"city": "TUTA", "long": -73.2333, "lat": 5.7, "cases": 127}, {"city": "CHITA", "long": -72.4167, "lat": 6.1667, "cases": 16}, {"city": "PESCA", "long": -73.05, "lat": 5.5833, "cases": 55}, {"city": "TIBANA", "long": -73.4, "lat": 5.3167, "cases": 127}, {"city": "SIACHOQUE", "long": -73.2333, "lat": 5.5, "cases": 135}, {"city": "MUZO", "long": -74.1073, "lat": 5.5313, "cases": 185}], "CASANARE": [{"city": "YOPAL", "long": -72.41, "lat": 5.35, "cases": 2402}, {"city": "AGUAZUL", "long": -72.5547, "lat": 5.1731, "cases": 600}, {"city": "TAURAMENA", "long": -72.75, "lat": 5.0167, "cases": 490}, {"city": "PAZ DE ARIPORO", "long": -71.9, "lat": 5.8833, "cases": 915}, {"city": "MONTERREY", "long": -72.8972, "lat": 4.8783, "cases": 341}, {"city": "MANI", "long": -72.2833, "lat": 4.8167, "cases": 116}, {"city": "TRINIDAD", "long": -71.6622, "lat": 5.4089, "cases": 150}, {"city": "NUNCHIA", "long": -72.2, "lat": 5.6333, "cases": 110}, {"city": "OROCUE", "long": -71.34, "lat": 4.7942, "cases": 133}], "CHOCO": [{"city": "QUIBDO", "long": -76.6581, "lat": 5.6922, "cases": 841}, {"city": "ISTMINA", "long": -76.6833, "lat": 5.1667, "cases": 133}, {"city": "TADO", "long": -76.5667, "lat": 5.2667, "cases": 84}, {"city": "CONDOTO", "long": -76.65, "lat": 5.1, "cases": 47}, {"city": "EL CARMEN DE ATRATO", "long": -76.1431, "lat": 5.8983, "cases": 19}, {"city": "BAGADO", "long": -76.4167, "lat": 5.4167, "cases": 4}, {"city": "UNGUIA", "long": -77.1, "lat": 8.05, "cases": 22}, {"city": "ACANDI", "long": -77.2333, "lat": 8.5333, "cases": 34}, {"city": "LLORO", "long": -76.5333, "lat": 5.5, "cases": 17}, {"city": "NUQUI", "long": -77.2667, "lat": 5.7167, "cases": 8}, {"city": "JURADO", "long": -77.7714, "lat": 7.1114, "cases": 6}], "ARAUCA": [{"city": "ARAUCA", "long": -70.7617, "lat": 7.0903, "cases": 1788}, {"city": "TAME", "long": -71.7333, "lat": 6.4667, "cases": 629}, {"city": "SARAVENA", "long": -71.8722, "lat": 6.9556, "cases": 492}, {"city": "ARAUQUITA", "long": -71.4356, "lat": 7.0303, "cases": 149}, {"city": "FORTUL", "long": -71.7756, "lat": 6.7922, "cases": 46}], "SAN": [{"city": "SAN ANDRES", "long": -81.7006, "lat": 12.5847, "cases": 1086}], "GUAVIARE": [{"city": "SAN JOSE DEL GUAVIARE", "long": -72.6333, "lat": 2.5667, "cases": 705}, {"city": "EL RETORNO", "long": -72.6278, "lat": 2.3306, "cases": 65}], "PUTUMAYO": [{"city": "MOCOA", "long": -76.6475, "lat": 1.15, "cases": 652}, {"city": "PUERTO ASIS", "long": -76.5, "lat": 0.5167, "cases": 545}, {"city": "ORITO", "long": -76.8708, "lat": 0.6661, "cases": 101}, {"city": "VALLE DEL GUAMUEZ", "long": -76.9053, "lat": 0.4253, "cases": 116}, {"city": "VILLAGARZON", "long": -76.6164, "lat": 1.0294, "cases": 163}, {"city": "PUERTO LEGUIZAMO", "long": -74.7806, "lat": -0.1939, "cases": 128}, {"city": "SIBUNDOY", "long": -76.9192, "lat": 1.2033, "cases": 175}, {"city": "PUERTO CAICEDO", "long": -76.6044, "lat": 0.685, "cases": 30}], "AMAZONAS": [{"city": "LETICIA", "long": -69.9333, "lat": -4.2167, "cases": 1234}, {"city": "PUERTO NARINO", "long": -70.3819, "lat": -3.7733, "cases": 65}], "VAUPES": [{"city": "MITU", "long": -70.1733, "lat": 1.1983, "cases": 243}], "GUAINIA": [{"city": "INIRIDA", "long": -67.9239, "lat": 3.8653, "cases": 483}], "VICHADA": [{"city": "PUERTO CARRENO", "long": -67.4667, "lat": 6.1833, "cases": 197}, {"city": "CUMARIBO", "long": -69.8, "lat": 4.4333, "cases": 18}, {"city": "LA PRIMAVERA", "long": -70.4092, "lat": 5.4906, "cases": 25}]}